tstype_py-0.1.5.dist-info/METADATA
tstype_py-0.1.5.dist-info/WHEEL
tstype_py/__init__.py
tstype_py/tstype_py.cpython-311-i386-linux-gnu.so
tstype_py-0.1.5.dist-info/RECORD
